MANIFEST.in
setup.py
include/android/log.h
include/cutils/log.h
include/log/log.h
include/log/logd.h
include/log/uio.h
include/utils/Errors.h
include/utils/Log.h
sensorfusion/__init__.py
sensorfusion.egg-info/PKG-INFO
sensorfusion.egg-info/SOURCES.txt
sensorfusion.egg-info/dependency_links.txt
sensorfusion.egg-info/top_level.txt
src/Fusion.cpp
src/Fusion.h
src/mat.h
src/pyglue.cpp
src/quat.h
src/traits.h
src/vec.h