Metadata-Version: 1.0
Name: sensorfusion
Version: 0.0.4
Summary: python sensor fusion, copied from Android
Home-page: https://github.com/asadoughi/sensorfusion
Author: Amir Sadoughi
Author-email: sensorfusion@princehonest.com
License: UNKNOWN
Platform: UNKNOWN
